{
    "name": "TimeTable",
    "fields": [
        {
            "fieldName": "weekday",
            "fieldType": "String",
            "fieldValidateRules": [
                "required"
            ]
        },
        {
            "fieldName": "number",
            "fieldType": "Integer",
            "fieldValidateRules": [
                "required"
            ]
        }
    ],
    "relationships": [
        {
            "relationshipName": "teacher",
            "otherEntityName": "teacher",
            "relationshipType": "many-to-one",
            "otherEntityField": "id"
        }
    ],
    "changelogDate": "20190225071038",
    "entityTableName": "time_table",
    "dto": "no",
    "pagination": "no",
    "service": "no",
    "jpaMetamodelFiltering": false,
    "fluentMethods": true,
    "clientRootFolder": "",
    "applications": "*"
}